steppygraph/__init__.py
steppygraph/machine.py
steppygraph/serialize.py
steppygraph/states.py
steppygraph/utils.py
steppygraph-0.1.10.dist-info/LICENSE
steppygraph-0.1.10.dist-info/METADATA
steppygraph-0.1.10.dist-info/WHEEL
steppygraph-0.1.10.dist-info/top_level.txt
steppygraph-0.1.10.dist-info/RECORD
