Metadata-Version: 2.1
Name: steppygraph
Version: 0.1.10
Summary: A Python DSL for AWS Step Functions
Home-page: https://github.com/mfrawley/steppy-graph
Author: Mark Frawley
Author-email: markfrawley+pypi@gmail.com
License: UNKNOWN
Platform: UNKNOWN
Classifier: Programming Language :: Python :: 3
Classifier: License :: OSI Approved :: MIT License
Classifier: Operating System :: OS Independent
